factorio_circuit_ast/ASTNode.py
factorio_circuit_ast/Comparison.py
factorio_circuit_ast/Constant.py
factorio_circuit_ast/DoubleNetwork.py
factorio_circuit_ast/Network.py
factorio_circuit_ast/Operand.py
factorio_circuit_ast/Operation.py
factorio_circuit_ast/Signal.py
factorio_circuit_ast/TwoSidedASTNode.py
factorio_circuit_ast/__init__.py
factorio_circuit_ast-0.0.0.dist-info/METADATA
factorio_circuit_ast-0.0.0.dist-info/WHEEL
factorio_circuit_ast-0.0.0.dist-info/entry_points.txt
factorio_circuit_ast-0.0.0.dist-info/top_level.txt
factorio_circuit_ast-0.0.0.dist-info/RECORD
