Metadata-Version: 2.1
Name: factorio-circuit-ast
Version: 0.0.0
Summary: A Package implementing an interpretable AST of factorio circuit logic
License: MIT License
Keywords: factorio,blueprint,ast,emulator,interpreter
Classifier: Programming Language :: Python :: 3
Classifier: Development Status :: 2 - Pre-Alpha
Classifier: Intended Audience :: Developers
Classifier: Intended Audience :: Information Technology
Classifier: License :: OSI Approved :: MIT License
Classifier: Operating System :: OS Independent
Classifier: Topic :: Software Development :: Interpreters
Classifier: Topic :: Software Development :: Testing
Classifier: Typing :: Typed
Requires-Dist: numpy (>=1.13)
Requires-Dist: factorio-draftsman (>=0.9.5)
